pyglog/__init__.py
pyglog/logger_factory.py
pyglog/providers/__init__.py
pyglog/providers/base_logger_factory.py
pyglog/providers/elasticsearch_logger_factory.py
pyglog/providers/opensearch_logger_factory.py
pyglog/providers/standard_logger.py
pyglog-1.0.0.dist-info/LICENCE
pyglog-1.0.0.dist-info/METADATA
pyglog-1.0.0.dist-info/WHEEL
pyglog-1.0.0.dist-info/top_level.txt
pyglog-1.0.0.dist-info/RECORD
