Metadata-Version: 2.1
Name: pyglog
Version: 1.0.0
Summary: Python generic logger for seamless integration with ELK, OpenSearch, and more.
License-File: LICENCE
